xtrshow/__init__.py
xtrshow/cli.py
xtrshow-0.1.2.dist-info/licenses/LICENSE
xtrshow-0.1.2.dist-info/METADATA
xtrshow-0.1.2.dist-info/WHEEL
xtrshow-0.1.2.dist-info/entry_points.txt
xtrshow-0.1.2.dist-info/top_level.txt
xtrshow-0.1.2.dist-info/RECORD
